search_vulns/CHANGELOG.md
search_vulns/README.md
search_vulns/__init__.py
search_vulns/cli.py
search_vulns/config.json
search_vulns/config_mariadb.json
search_vulns/core.py
search_vulns/cpe_version.py
search_vulns/install.sh
search_vulns/installer.py
search_vulns/updater.py
search_vulns/vulnerability.py
search_vulns/web_server.py
search_vulns/wsgi.py
search_vulns/modules/__init__.py
search_vulns/modules/utils.py
search_vulns/modules/cpe_search/__init__.py
search_vulns/modules/cpe_search/build.py
search_vulns/modules/cpe_search/search_vulns_cpe_search.py
search_vulns/modules/cpe_search/resources/debian_equiv_cpes.json
search_vulns/modules/cpe_search/resources/man_equiv_cpes.json
search_vulns/modules/end_of_life_date/__init__.py
search_vulns/modules/end_of_life_date/build.py
search_vulns/modules/end_of_life_date/eold_hardcoded_matches.json
search_vulns/modules/end_of_life_date/search_vulns_eold.py
search_vulns/modules/epss/__init__.py
search_vulns/modules/epss/search_vulns_epss.py
search_vulns/modules/exploit_db/__init__.py
search_vulns/modules/exploit_db/build.py
search_vulns/modules/exploit_db/search_vulns_edb.py
search_vulns/modules/ghsa/__init__.py
search_vulns/modules/ghsa/build.py
search_vulns/modules/ghsa/ghsa_hardcoded_matches.json
search_vulns/modules/ghsa/search_vulns_ghsa.py
search_vulns/modules/linux_distro_backpatches/__init__.py
search_vulns/modules/linux_distro_backpatches/hardcoded_pkg_cpe_map.json
search_vulns/modules/linux_distro_backpatches/search_vulns_download_resources.py
search_vulns/modules/linux_distro_backpatches/utils.py
search_vulns/modules/linux_distro_backpatches/debian/__init__.py
search_vulns/modules/linux_distro_backpatches/debian/build.py
search_vulns/modules/linux_distro_backpatches/debian/search_vulns_debian.py
search_vulns/modules/linux_distro_backpatches/redhat/__init__.py
search_vulns/modules/linux_distro_backpatches/redhat/build.py
search_vulns/modules/linux_distro_backpatches/redhat/search_vulns_redhat.py
search_vulns-0.9.1.dist-info/METADATA
search_vulns-0.9.1.dist-info/WHEEL
search_vulns-0.9.1.dist-info/entry_points.txt
search_vulns-0.9.1.dist-info/licenses/LICENSE
search_vulns-0.9.1.dist-info/RECORD
