Metadata-Version: 2.4
Name: search_vulns
Version: 0.9.1
Summary: Search for known vulnerabilities in software using software titles or a CPE 2.3 string.
Project-URL: Homepage, https://search-vulns.com
Project-URL: Documentation, https://github.com/ra1nb0rn/search_vulns
Project-URL: Repository, https://github.com/ra1nb0rn/search_vulns
Project-URL: Issues, https://github.com/ra1nb0rn/search_vulns/issues
Author-email: Dustin Born <search.vulns1@gmail.com>
License-Expression: MIT
License-File: LICENSE
Keywords: cpe,cve,exploit,nvd,pentest,security,vulnerability
Classifier: Development Status :: 4 - Beta
Classifier: Intended Audience :: Developers
Classifier: Intended Audience :: Information Technology
Classifier: Intended Audience :: System Administrators
Classifier: License :: OSI Approved :: MIT License
Classifier: Programming Language :: Python :: 3
Classifier: Programming Language :: Python :: 3.10
Classifier: Topic :: Security
Classifier: Topic :: System :: Systems Administration
Requires-Python: >=3.10
Requires-Dist: aiohttp
Requires-Dist: aiolimiter
Requires-Dist: cpe-search==0.1.7
Requires-Dist: cvss
Requires-Dist: requests
Requires-Dist: tqdm
Requires-Dist: ujson
Requires-Dist: univers
Provides-Extra: all
Requires-Dist: aiohttp; extra == 'all'
Requires-Dist: aiolimiter; extra == 'all'
Requires-Dist: cpe-search==0.1.7; extra == 'all'
Requires-Dist: cvss; extra == 'all'
Requires-Dist: flask; extra == 'all'
Requires-Dist: gevent; extra == 'all'
Requires-Dist: gunicorn; extra == 'all'
Requires-Dist: mariadb==1.1.12; extra == 'all'
Requires-Dist: markdown; extra == 'all'
Requires-Dist: requests; extra == 'all'
Requires-Dist: tqdm; extra == 'all'
Requires-Dist: ujson; extra == 'all'
Requires-Dist: univers; extra == 'all'
Provides-Extra: dev
Requires-Dist: black; extra == 'dev'
Requires-Dist: isort; extra == 'dev'
Requires-Dist: pylint; extra == 'dev'
Requires-Dist: ruff; extra == 'dev'
Provides-Extra: mariadb
Requires-Dist: mariadb==1.1.12; extra == 'mariadb'
Provides-Extra: web
Requires-Dist: flask; extra == 'web'
Requires-Dist: gevent; extra == 'web'
Requires-Dist: gunicorn; extra == 'web'
Requires-Dist: markdown; extra == 'web'
